trix_widget/__init__.py
trix_widget/fields.py
trix_widget/version.py
trix_widget/widgets.py
trix_widget/static/trix/trix.css
trix_widget/static/trix/trix.min.js
trix_widget/templates/trix_widget.html
django_trix_widget-1.0.4.dist-info/METADATA
django_trix_widget-1.0.4.dist-info/WHEEL
django_trix_widget-1.0.4.dist-info/top_level.txt
django_trix_widget-1.0.4.dist-info/RECORD
