Metadata-Version: 2.1
Name: django-trix-widget
Version: 1.0.4
Summary: Trix widget for Django
Home-page: https://github.com/bboogaard/django-trix-widget
Author: Bram Boogaard
Author-email: padawan@hetnet.nl
License: MIT License
Keywords: Django Trix widget
Classifier: Development Status :: 3 - Alpha
Requires-Dist: pytest
Requires-Dist: pytest-cov
Requires-Dist: pytest-django ~=4.5.2
Requires-Dist: django ~=3.2.23
Requires-Dist: pyquery ~=2.0.0
Requires-Dist: bleach ~=6.1.0
